rtl/alu.v
`timescale 1ns/1ps

module alu (

    input  wire [31:0] a,
    input  wire [31:0] b,
    input  wire [3:0]  alu_control,

    output reg  [31:0] result,
    output wire        zero

);

always @(*) begin

    case (alu_control)

        4'b0000: result = a + b;                      // ADD
        4'b0001: result = a - b;                      // SUB
        4'b0010: result = a & b;                      // AND
        4'b0011: result = a | b;                      // OR
        4'b0100: result = a ^ b;                      // XOR
        4'b0101: result = a << b[4:0];                // SLL
        4'b0110: result = a >> b[4:0];                // SRL
        4'b0111: result = ($signed(a) < $signed(b)) ? 32'd1 : 32'd0; // SLT

        default: result = 32'd0;

    endcase

end

assign zero = (result == 32'd0);

endmodule

tb/alu_tb.v
`timescale 1ns/1ps

module alu_tb;

    reg  [31:0] a;
    reg  [31:0] b;
    reg  [3:0]  alu_control;

    wire [31:0] result;
    wire zero;

    // Instantiate DUT
    alu dut (
        .a(a),
        .b(b),
        .alu_control(alu_control),
        .result(result),
        .zero(zero)
    );

    initial begin

        $dumpfile("alu.vcd");
        $dumpvars(0, alu_tb);

        // ADD
        a = 20; b = 10; alu_control = 4'b0000;
        #10;
        $display("ADD : %d", result);

        // SUB
        a = 20; b = 10; alu_control = 4'b0001;
        #10;
        $display("SUB : %d", result);

        // AND
        a = 32'hF0F0F0F0; b = 32'h0F0F0F0F; alu_control = 4'b0010;
        #10;
        $display("AND : %h", result);

        // OR
        alu_control = 4'b0011;
        #10;
        $display("OR  : %h", result);

        // XOR
        alu_control = 4'b0100;
        #10;
        $display("XOR : %h", result);

        // Shift Left
        a = 1; b = 4; alu_control = 4'b0101;
        #10;
        $display("SLL : %d", result);

        // Shift Right
        a = 16; b = 2; alu_control = 4'b0110;
        #10;
        $display("SRL : %d", result);

        // Set Less Than
        a = 5; b = 10; alu_control = 4'b0111;
        #10;
        $display("SLT : %d", result);

        // Zero flag
        a = 10; b = 10; alu_control = 4'b0001;
        #10;
        $display("ZERO = %b", zero);

        $finish;

    end

endmodule

alu.vcd
$date
	Wed Jul 22 13:23:35 2026
$end
$version
	Icarus Verilog
$end
$timescale
	1ps
$end
$scope module alu_tb $end
$var wire 1 ! zero $end
$var wire 32 " result [31:0] $end
$var reg 32 # a [31:0] $end
$var reg 4 $ alu_control [3:0] $end
$var reg 32 % b [31:0] $end
$scope module dut $end
$var wire 32 & a [31:0] $end
$var wire 4 ' alu_control [3:0] $end
$var wire 32 ( b [31:0] $end
$var wire 1 ! zero $end
$var reg 32 ) result [31:0] $end
$upscope $end
$upscope $end
$enddefinitions $end
$comment Show the parameter values. $end
$dumpall
$end
#0
$dumpvars
b11110 )
b1010 (
b0 '
b10100 &
b1010 %
b0 $
b10100 #
b11110 "
0!
$end
#10000
b1010 "
b1010 )
b1 $
b1 '
#20000
1!
b0 "
b0 )
b10 $
b10 '
b1111000011110000111100001111 %
b1111000011110000111100001111 (
b11110000111100001111000011110000 #
b11110000111100001111000011110000 &
#30000
0!
b11111111111111111111111111111111 "
b11111111111111111111111111111111 )
b11 $
b11 '
#40000
b100 $
b100 '
#50000
b10000 "
b10000 )
b101 $
b101 '
b100 %
b100 (
b1 #
b1 &
#60000
b100 "
b100 )
b110 $
b110 '
b10 %
b10 (
b10000 #
b10000 &
#70000
b1 "
b1 )
b111 $
b111 '
b1010 %
b1010 (
b101 #
b101 &
#80000
1!
b0 "
b0 )
b1 $
b1 '
b1010 #
b1010 &
