rtl/alu_control.v
`timescale 1ns/1ps

module alu_control (

    input  wire [1:0] ALUOp,
    input  wire [2:0] funct3,
    input  wire [6:0] funct7,

    output reg  [3:0] alu_ctrl

);

always @(*) begin

    case (ALUOp)

        // Load/Store -> ADD
        2'b00:
            alu_ctrl = 4'b0000;

        // Branch -> SUB
        2'b01:
            alu_ctrl = 4'b0001;

        // R-Type / I-Type
        2'b10: begin

            case ({funct7, funct3})

                10'b0000000_000: alu_ctrl = 4'b0000; // ADD
                10'b0100000_000: alu_ctrl = 4'b0001; // SUB
                10'b0000000_111: alu_ctrl = 4'b0010; // AND
                10'b0000000_110: alu_ctrl = 4'b0011; // OR
                10'b0000000_100: alu_ctrl = 4'b0100; // XOR
                10'b0000000_001: alu_ctrl = 4'b0101; // SLL
                10'b0000000_101: alu_ctrl = 4'b0110; // SRL
                10'b0000000_010: alu_ctrl = 4'b0111; // SLT

                default:
                    alu_ctrl = 4'b0000;

            endcase

        end

        default:
            alu_ctrl = 4'b0000;

    endcase

end

endmodule

tb/alu_control_tb.v
`timescale 1ns/1ps

module alu_control_tb;

    reg  [1:0] ALUOp;
    reg  [2:0] funct3;
    reg  [6:0] funct7;

    wire [3:0] alu_ctrl;

    // Instantiate DUT
    alu_control dut (
        .ALUOp(ALUOp),
        .funct3(funct3),
        .funct7(funct7),
        .alu_ctrl(alu_ctrl)
    );

    initial begin

        $dumpfile("alu_control.vcd");
        $dumpvars(0, alu_control_tb);

        // Load/Store -> ADD
        ALUOp = 2'b00;
        funct3 = 3'b000;
        funct7 = 7'b0000000;
        #10;
        $display("LOAD/STORE : alu_ctrl = %b", alu_ctrl);

        // Branch -> SUB
        ALUOp = 2'b01;
        #10;
        $display("BRANCH     : alu_ctrl = %b", alu_ctrl);

        // ADD
        ALUOp = 2'b10;
        funct3 = 3'b000;
        funct7 = 7'b0000000;
        #10;
        $display("ADD        : alu_ctrl = %b", alu_ctrl);

        // SUB
        funct7 = 7'b0100000;
        #10;
        $display("SUB        : alu_ctrl = %b", alu_ctrl);

        // AND
        funct3 = 3'b111;
        funct7 = 7'b0000000;
        #10;
        $display("AND        : alu_ctrl = %b", alu_ctrl);

        // OR
        funct3 = 3'b110;
        #10;
        $display("OR         : alu_ctrl = %b", alu_ctrl);

        // XOR
        funct3 = 3'b100;
        #10;
        $display("XOR        : alu_ctrl = %b", alu_ctrl);

        // SLL
        funct3 = 3'b001;
        #10;
        $display("SLL        : alu_ctrl = %b", alu_ctrl);

        // SRL
        funct3 = 3'b101;
        #10;
        $display("SRL        : alu_ctrl = %b", alu_ctrl);

        // SLT
        funct3 = 3'b010;
        #10;
        $display("SLT        : alu_ctrl = %b", alu_ctrl);

        $finish;

    end

endmodule

alu_control.vcd
$date
	Wed Jul 22 18:02:31 2026
$end
$version
	Icarus Verilog
$end
$timescale
	1ps
$end
$scope module alu_control_tb $end
$var wire 4 ! alu_ctrl [3:0] $end
$var reg 2 " ALUOp [1:0] $end
$var reg 3 # funct3 [2:0] $end
$var reg 7 $ funct7 [6:0] $end
$scope module dut $end
$var wire 2 % ALUOp [1:0] $end
$var wire 3 & funct3 [2:0] $end
$var wire 7 ' funct7 [6:0] $end
$var reg 4 ( alu_ctrl [3:0] $end
$upscope $end
$upscope $end
$enddefinitions $end
$comment Show the parameter values. $end
$dumpall
$end
#0
$dumpvars
b0 (
b0 '
b0 &
b0 %
b0 $
b0 #
b0 "
b0 !
$end
#10000
b1 !
b1 (
b1 "
b1 %
#20000
b0 !
b0 (
b10 "
b10 %
#30000
b1 !
b1 (
b100000 $
b100000 '
#40000
b10 !
b10 (
b0 $
b0 '
b111 #
b111 &
#50000
b11 !
b11 (
b110 #
b110 &
#60000
b100 !
b100 (
b100 #
b100 &
#70000
b101 !
b101 (
b1 #
b1 &
#80000
b110 !
b110 (
b101 #
b101 &
#90000
b111 !
b111 (
b10 #
b10 &
