rtl/riscv_pipeline/pc_plus4.v
module pc_plus4(

input [31:0] pc,

output [31:0] next_pc

);

assign next_pc = pc + 32'd4;

endmodule

rtl/riscv_pipeline/program_counter.v
module program_counter(

input clk,
input rst,

input [31:0] next_pc,

output reg [31:0] pc

);

always @(posedge clk or posedge rst)
begin

    if(rst)
        pc <= 32'd0;

    else
        pc <= next_pc;

end

endmodule

tb/riscv_pipeline/program_counter_tb.v
`timescale 1ns/1ps

module program_counter_tb;

reg clk;
reg rst;

wire [31:0] pc;
wire [31:0] next_pc;

program_counter PC(

.clk(clk),
.rst(rst),

.next_pc(next_pc),

.pc(pc)

);

pc_plus4 ADDER(

.pc(pc),

.next_pc(next_pc)

);

always #5 clk = ~clk;

initial
begin

$dumpfile("program_counter.vcd");
$dumpvars(0,program_counter_tb);

clk = 0;
rst = 1;

#20;

rst = 0;

#100;

$finish;

end

endmodule

program_counter.vcd
$date
	Wed Aug  5 16:42:31 2026
$end
$version
	Icarus Verilog
$end
$timescale
	1ps
$end
$scope module program_counter_tb $end
$var wire 32 ! pc [31:0] $end
$var wire 32 " next_pc [31:0] $end
$var reg 1 # clk $end
$var reg 1 $ rst $end
$scope module ADDER $end
$var wire 32 % pc [31:0] $end
$var wire 32 & next_pc [31:0] $end
$upscope $end
$scope module PC $end
$var wire 1 # clk $end
$var wire 32 ' next_pc [31:0] $end
$var wire 1 $ rst $end
$var reg 32 ( pc [31:0] $end
$upscope $end
$upscope $end
$enddefinitions $end
$comment Show the parameter values. $end
$dumpall
$end
#0
$dumpvars
b0 (
b100 '
b100 &
b0 %
1$
0#
b100 "
b0 !
$end
#5000
1#
#10000
0#
#15000
1#
#20000
0#
0$
#25000
b1000 "
b1000 &
b1000 '
b100 !
b100 %
b100 (
1#
#30000
0#
#35000
b1100 "
b1100 &
b1100 '
b1000 !
b1000 %
b1000 (
1#
#40000
0#
#45000
b10000 "
b10000 &
b10000 '
b1100 !
b1100 %
b1100 (
1#
#50000
0#
#55000
b10100 "
b10100 &
b10100 '
b10000 !
b10000 %
b10000 (
1#
#60000
0#
#65000
b11000 "
b11000 &
b11000 '
b10100 !
b10100 %
b10100 (
1#
#70000
0#
#75000
b11100 "
b11100 &
b11100 '
b11000 !
b11000 %
b11000 (
1#
#80000
0#
#85000
b100000 "
b100000 &
b100000 '
b11100 !
b11100 %
b11100 (
1#
#90000
0#
#95000
b100100 "
b100100 &
b100100 '
b100000 !
b100000 %
b100000 (
1#
#100000
0#
#105000
b101000 "
b101000 &
b101000 '
b100100 !
b100100 %
b100100 (
1#
#110000
0#
#115000
b101100 "
b101100 &
b101100 '
b101000 !
b101000 %
b101000 (
1#
