rtl/program_counter.v
`timescale 1ns/1ps

// Module : Program Counter
// Description : Stores the address of the next instruction

module program_counter (

    input wire clk,
    input wire rst,

    input wire [31:0] pc_next,

    output reg [31:0] pc

);

always @(posedge clk) begin

    if (rst)
        pc <= 32'h00000000;

    else
        pc <= pc_next;

end

endmodule

tb/program_counter_tb.v
`timescale 1ns/1ps

module program_counter_tb;

    reg clk;
    reg rst;
    reg [31:0] pc_next;
    wire [31:0] pc;

    // Instantiate DUT
    program_counter dut (
        .clk(clk),
        .rst(rst),
        .pc_next(pc_next),
        .pc(pc)
    );

    // Clock generation (10 ns period)
    always #5 clk = ~clk;

    initial begin
        // Dump waveform
        $dumpfile("program_counter.vcd");
$dumpvars(0, program_counter_tb);

        // Initialize signals
        clk = 0;
        rst = 1;
        pc_next = 32'd0;

        // Hold reset
        #10;
        rst = 0;

        // Update PC values
        #10 pc_next = 32'd4;
        #10 pc_next = 32'd8;
        #10 pc_next = 32'd12;
        #10 pc_next = 32'd16;

        #20;
        $finish;
    end;

endmodule

program_counter.vcd
$date
	Tue Jul 21 18:03:45 2026
$end
$version
	Icarus Verilog
$end
$timescale
	1ps
$end
$scope module program_counter_tb $end
$var wire 32 ! pc [31:0] $end
$var reg 1 " clk $end
$var reg 32 # pc_next [31:0] $end
$var reg 1 $ rst $end
$scope module dut $end
$var wire 1 " clk $end
$var wire 32 % pc_next [31:0] $end
$var wire 1 $ rst $end
$var reg 32 & pc [31:0] $end
$upscope $end
$upscope $end
$enddefinitions $end
$comment Show the parameter values. $end
$dumpall
$end
#0
$dumpvars
bx &
b0 %
1$
b0 #
0"
bx !
$end
#5000
b0 !
b0 &
1"
#10000
0"
0$
#15000
1"
#20000
0"
b100 #
b100 %
#25000
b100 !
b100 &
1"
#30000
0"
b1000 #
b1000 %
#35000
b1000 !
b1000 &
1"
#40000
0"
b1100 #
b1100 %
#45000
b1100 !
b1100 &
1"
#50000
0"
b10000 #
b10000 %
#55000
b10000 !
b10000 &
1"
