rtl/data_memory.v
`timescale 1ns/1ps

module data_memory (

    input  wire        clk,
    input  wire        MemRead,
    input  wire        MemWrite,
    input  wire [31:0] addr,
    input  wire [31:0] write_data,

    output reg  [31:0] read_data

);

    // 256 x 32-bit memory
    reg [31:0] memory [0:255];

    integer i;

    // Initialize memory
    initial begin
        for (i = 0; i < 256; i = i + 1)
            memory[i] = 32'd0;
    end

    // Write Operation (Synchronous)
    always @(posedge clk) begin
        if (MemWrite)
            memory[addr[9:2]] <= write_data;
    end

    // Read Operation (Combinational)
    always @(*) begin
        if (MemRead)
            read_data = memory[addr[9:2]];
        else
            read_data = 32'd0;
    end

endmodule

rtl/alu.v
`timescale 1ns/1ps

module alu (

    input  wire [31:0] a,
    input  wire [31:0] b,
    input  wire [3:0]  alu_control,

    output reg  [31:0] result,
    output wire        zero

);

always @(*) begin

    case (alu_control)

        4'b0000: result = a + b;                      // ADD
        4'b0001: result = a - b;                      // SUB
        4'b0010: result = a & b;                      // AND
        4'b0011: result = a | b;                      // OR
        4'b0100: result = a ^ b;                      // XOR
        4'b0101: result = a << b[4:0];                // SLL
        4'b0110: result = a >> b[4:0];                // SRL
        4'b0111: result = ($signed(a) < $signed(b)) ? 32'd1 : 32'd0; // SLT

        default: result = 32'd0;

    endcase

end

assign zero = (result == 32'd0);

endmodule

rtl/alu_control.v
`timescale 1ns/1ps

module alu_control (

    input  wire [1:0] ALUOp,
    input  wire [2:0] funct3,
    input  wire [6:0] funct7,

    output reg  [3:0] alu_ctrl

);

always @(*) begin

    case (ALUOp)

        // Load/Store -> ADD
        2'b00:
            alu_ctrl = 4'b0000;

        // Branch -> SUB
        2'b01:
            alu_ctrl = 4'b0001;

        // R-Type / I-Type
        2'b10: begin

            case ({funct7, funct3})

                10'b0000000_000: alu_ctrl = 4'b0000; // ADD
                10'b0100000_000: alu_ctrl = 4'b0001; // SUB
                10'b0000000_111: alu_ctrl = 4'b0010; // AND
                10'b0000000_110: alu_ctrl = 4'b0011; // OR
                10'b0000000_100: alu_ctrl = 4'b0100; // XOR
                10'b0000000_001: alu_ctrl = 4'b0101; // SLL
                10'b0000000_101: alu_ctrl = 4'b0110; // SRL
                10'b0000000_010: alu_ctrl = 4'b0111; // SLT

                default:
                    alu_ctrl = 4'b0000;

            endcase

        end

        default:
            alu_ctrl = 4'b0000;

    endcase

end

endmodule

rtl/register_file.v
`timescale 1ns/1ps

module register_file (

    input wire clk,
    input wire rst,

    input wire we,

    input wire [4:0] rs1,
    input wire [4:0] rs2,
    input wire [4:0] rd,

    input wire [31:0] write_data,

    output wire [31:0] read_data1,
    output wire [31:0] read_data2

);

    // 32 Registers
    reg [31:0] registers [0:31];

    integer i;

    // Reset and Write Logic
    always @(posedge clk) begin

        if (rst) begin

            for(i = 0; i < 32; i = i + 1)
                registers[i] <= 32'b0;

        end
        else if (we && (rd != 0)) begin

            registers[rd] <= write_data;

        end

    end

    // Combinational Read
    assign read_data1 = (rs1 == 0) ? 32'b0 : registers[rs1];
    assign read_data2 = (rs2 == 0) ? 32'b0 : registers[rs2];

endmodule

rtl/immediate_generator.v
`timescale 1ns/1ps

module immediate_generator(

    input  wire [31:0] instruction,
    output reg  [31:0] immediate

);

always @(*) begin

    case (instruction[6:0])

        // I-Type (ADDI, LW, JALR)
        7'b0010011,
        7'b0000011,
        7'b1100111:
            immediate = {{20{instruction[31]}}, instruction[31:20]};

        // S-Type (SW)
        7'b0100011:
            immediate = {{20{instruction[31]}},
                         instruction[31:25],
                         instruction[11:7]};

        // B-Type (BEQ, BNE)
        7'b1100011:
            immediate = {{19{instruction[31]}},
                         instruction[31],
                         instruction[7],
                         instruction[30:25],
                         instruction[11:8],
                         1'b0};

        // U-Type (LUI, AUIPC)
        7'b0110111,
        7'b0010111:
            immediate = {instruction[31:12],12'b0};

        // J-Type (JAL)
        7'b1101111:
            immediate = {{11{instruction[31]}},
                         instruction[31],
                         instruction[19:12],
                         instruction[20],
                         instruction[30:21],
                         1'b0};

        default:
            immediate = 32'd0;

    endcase

end

endmodule

rtl/control_unit.v
`timescale 1ns/1ps

module control_unit(

    input  wire [6:0] opcode,

    output reg RegWrite,
    output reg ALUSrc,
    output reg MemRead,
    output reg MemWrite,
    output reg MemtoReg,
    output reg Branch,
    output reg Jump,
    output reg [1:0] ALUOp

);

always @(*) begin

    // Default values
    RegWrite = 0;
    ALUSrc   = 0;
    MemRead  = 0;
    MemWrite = 0;
    MemtoReg = 0;
    Branch   = 0;
    Jump     = 0;
    ALUOp    = 2'b00;

    case(opcode)

        // R-Type
        7'b0110011: begin
            RegWrite = 1;
            ALUSrc   = 0;
            ALUOp    = 2'b10;
        end

        // I-Type Arithmetic
        7'b0010011: begin
            RegWrite = 1;
            ALUSrc   = 1;
            ALUOp    = 2'b10;
        end

        // Load
        7'b0000011: begin
            RegWrite = 1;
            ALUSrc   = 1;
            MemRead  = 1;
            MemtoReg = 1;
            ALUOp    = 2'b00;
        end

        // Store
        7'b0100011: begin
            ALUSrc   = 1;
            MemWrite = 1;
            ALUOp    = 2'b00;
        end

        // Branch
        7'b1100011: begin
            Branch = 1;
            ALUOp  = 2'b01;
        end

        // JAL
        7'b1101111: begin
            Jump     = 1;
            RegWrite = 1;
        end

        default: begin
            // Keep defaults
        end

    endcase

end

endmodule

rtl/instruction_memory.v
`timescale 1ns/1ps

// Module: Instruction Memory

// Stores 32-bit RISC-V instructions.

module instruction_memory(

    input  wire [31:0] addr,
    output wire [31:0] instruction

);

    // 256 x 32-bit instruction memory
    reg [31:0] memory [0:255];

    // Initialize instructions
    initial begin

        // addi x1, x0, 5
        memory[0] = 32'h00500093;

        // addi x2, x0, 10
        memory[1] = 32'h00A00113;

        // add x3, x1, x2
        memory[2] = 32'h002081B3;

        // nop
        memory[3] = 32'h00000013;

    end

    // Word aligned access
    assign instruction = memory[addr[9:2]];

endmodule

rtl/program_counter.v
`timescale 1ns/1ps

// Module : Program Counter
// Description : Stores the address of the next instruction

module program_counter (

    input wire clk,
    input wire rst,

    input wire [31:0] pc_next,

    output reg [31:0] pc

);

always @(posedge clk or posedge rst) begin
    if (rst)
        pc <= 32'd0;
    else
        pc <= pc+32'd4;
end

endmodule

rtl/riscv_cpu.v
`timescale 1ns/1ps

module riscv_cpu(

    input wire clk,
    input wire rst

);

    // Internal Wires
    wire [31:0] pc;
    wire [31:0] instruction;

    wire [31:0] immediate;
    wire [31:0] mem_data;

    // Control Signals
    wire RegWrite;
    wire ALUSrc;
    wire MemRead;
    wire MemWrite;
    wire MemtoReg;
    wire Branch;
    wire Jump;
    wire [1:0] ALUOp;

    // Register File
    wire [31:0] read_data1;
    wire [31:0] read_data2;
    wire [31:0] write_data;

    // ALU Control
    wire [3:0] alu_ctrl;

// ALU
    wire [31:0] alu_input2;
    wire [31:0] alu_result;
    wire zero;

    // Program Counter
    program_counter PC (

        .clk(clk),
        .rst(rst),
        .pc(pc)

    );

    // Instruction Memory
    instruction_memory IM (

        .addr(pc),
        .instruction(instruction)

    );

// Control Unit

    control_unit CU (

        .opcode(instruction[6:0]),

        .RegWrite(RegWrite),
        .ALUSrc(ALUSrc),
        .MemRead(MemRead),
        .MemWrite(MemWrite),
        .MemtoReg(MemtoReg),
        .Branch(Branch),
        .Jump(Jump),
        .ALUOp(ALUOp)

);

// Immediate Generator
    immediate_generator IMM (

        .instruction(instruction),
        .immediate(immediate)

);

// Register File
    register_file RF (

        .clk(clk),
        .rst(rst),
        .we(RegWrite),

        .rs1(instruction[19:15]),
        .rs2(instruction[24:20]),
        .rd(instruction[11:7]),

        .write_data(write_data),

        .read_data1(read_data1),
        .read_data2(read_data2)

);

// ALU Control
    alu_control ALUCTRL (

        .ALUOp(ALUOp),
        .funct3(instruction[14:12]),
        .funct7(instruction[31:25]),
        .alu_ctrl(alu_ctrl)

);

// ALU
    alu ALU (

        .a(read_data1),
        .b(alu_input2),
        .alu_control(alu_ctrl),
        .result(alu_result),
        .zero(zero)

);
    data_memory DM (

        .clk(clk),
        .MemRead(MemRead),
        .MemWrite(MemWrite),

        .addr(alu_result),
        .write_data(read_data2),

        .read_data(mem_data)

);

    assign write_data = (MemtoReg) ? mem_data : alu_result;
    assign alu_input2 = (ALUSrc) ? immediate : read_data2;
    
endmodule

tb/riscv_cpu_tb.v
`timescale 1ns/1ps

module riscv_cpu_tb;

    reg clk;
    reg rst;

    // Instantiate CPU
    riscv_cpu DUT (

        .clk(clk),
        .rst(rst)

    );

    // Clock Generation
    always #5 clk = ~clk;

    initial begin

        $dumpfile("riscv_cpu.vcd");
        $dumpvars(0, riscv_cpu_tb);

        clk = 0;
        rst = 1;

        // Hold reset
        #20;
        rst = 0;

        // Run CPU
        #200;

        $finish;

    end

endmodule

riscv_cpu.vcd
$date
	Thu Jul 23 19:33:42 2026
$end
$version
	Icarus Verilog
$end
$timescale
	1ps
$end
$scope module riscv_cpu_tb $end
$var reg 1 ! clk $end
$var reg 1 " rst $end
$scope module DUT $end
$var wire 1 ! clk $end
$var wire 1 " rst $end
$var wire 1 # zero $end
$var wire 32 $ write_data [31:0] $end
$var wire 32 % read_data2 [31:0] $end
$var wire 32 & read_data1 [31:0] $end
$var wire 32 ' pc [31:0] $end
$var wire 32 ( mem_data [31:0] $end
$var wire 32 ) instruction [31:0] $end
$var wire 32 * immediate [31:0] $end
$var wire 32 + alu_result [31:0] $end
$var wire 32 , alu_input2 [31:0] $end
$var wire 4 - alu_ctrl [3:0] $end
$var wire 1 . RegWrite $end
$var wire 1 / MemtoReg $end
$var wire 1 0 MemWrite $end
$var wire 1 1 MemRead $end
$var wire 1 2 Jump $end
$var wire 1 3 Branch $end
$var wire 1 4 ALUSrc $end
$var wire 2 5 ALUOp [1:0] $end
$scope module ALU $end
$var wire 32 6 b [31:0] $end
$var wire 1 # zero $end
$var wire 4 7 alu_control [3:0] $end
$var wire 32 8 a [31:0] $end
$var reg 32 9 result [31:0] $end
$upscope $end
$scope module ALUCTRL $end
$var wire 3 : funct3 [2:0] $end
$var wire 7 ; funct7 [6:0] $end
$var wire 2 < ALUOp [1:0] $end
$var reg 4 = alu_ctrl [3:0] $end
$upscope $end
$scope module CU $end
$var wire 7 > opcode [6:0] $end
$var reg 2 ? ALUOp [1:0] $end
$var reg 1 4 ALUSrc $end
$var reg 1 3 Branch $end
$var reg 1 2 Jump $end
$var reg 1 1 MemRead $end
$var reg 1 0 MemWrite $end
$var reg 1 / MemtoReg $end
$var reg 1 . RegWrite $end
$upscope $end
$scope module DM $end
$var wire 1 1 MemRead $end
$var wire 1 0 MemWrite $end
$var wire 32 @ addr [31:0] $end
$var wire 1 ! clk $end
$var wire 32 A write_data [31:0] $end
$var reg 32 B read_data [31:0] $end
$var integer 32 C i [31:0] $end
$upscope $end
$scope module IM $end
$var wire 32 D instruction [31:0] $end
$var wire 32 E addr [31:0] $end
$upscope $end
$scope module IMM $end
$var wire 32 F instruction [31:0] $end
$var reg 32 G immediate [31:0] $end
$upscope $end
$scope module PC $end
$var wire 1 ! clk $end
$var wire 32 H pc_next [31:0] $end
$var wire 1 " rst $end
$var reg 32 I pc [31:0] $end
$upscope $end
$scope module RF $end
$var wire 1 ! clk $end
$var wire 5 J rd [4:0] $end
$var wire 5 K rs1 [4:0] $end
$var wire 5 L rs2 [4:0] $end
$var wire 1 " rst $end
$var wire 1 . we $end
$var wire 32 M write_data [31:0] $end
$var wire 32 N read_data2 [31:0] $end
$var wire 32 O read_data1 [31:0] $end
$var integer 32 P i [31:0] $end
$upscope $end
$upscope $end
$upscope $end
$enddefinitions $end
$comment Show the parameter values. $end
$dumpall
$end
#0
$dumpvars
bx P
b0 O
bx N
b101 M
b101 L
b0 K
b1 J
b0 I
bz H
b101 G
b10100000000000010010011 F
b0 E
b10100000000000010010011 D
b100000000 C
b0 B
bx A
b101 @
b10 ?
b10011 >
b0 =
b10 <
b0 ;
b0 :
b101 9
b0 8
b0 7
b101 6
b10 5
14
03
02
01
00
0/
1.
b0 -
b101 ,
b101 +
b101 *
b10100000000000010010011 )
b0 (
b0 '
b0 &
bx %
b101 $
0#
1"
0!
$end
#5000
b0 %
b0 A
b0 N
b100000 P
1!
#10000
0!
#15000
b100000 P
1!
#20000
0!
0"
#25000
b1010 $
b1010 M
b1010 +
b1010 9
b1010 @
b1010 ,
b1010 6
b1010 *
b1010 G
b10 J
b1010 L
b101000000000000100010011 )
b101000000000000100010011 D
b101000000000000100010011 F
b100 '
b100 E
b100 I
1!
#30000
0!
#35000
b1111 $
b1111 M
b1111 +
b1111 9
b1111 @
b1010 %
b1010 A
b1010 N
b101 &
b101 8
b101 O
b10 5
b10 <
b10 ?
04
1.
b0 *
b0 G
b11 J
b10 L
b1 K
b110011 >
b1000001000000110110011 )
b1000001000000110110011 D
b1000001000000110110011 F
b1000 '
b1000 E
b1000 I
1!
#40000
0!
#45000
b0 $
b0 M
1#
b0 +
b0 9
b0 @
b0 ,
b0 6
b0 %
b0 A
b0 N
b0 &
b0 8
b0 O
14
b10 5
b10 <
b10 ?
1.
b0 J
b0 L
b0 K
b10011 >
b10011 )
b10011 D
b10011 F
b1100 '
b1100 E
b1100 I
1!
#50000
0!
#55000
bx $
bx M
x#
bx +
bx 9
bx @
bx ,
bx 6
bx %
bx A
bx N
bx &
bx 8
bx O
b0 5
b0 <
b0 ?
04
0.
bx ;
bx :
bx J
bx L
bx K
bx >
bx )
bx D
bx F
b10000 '
b10000 E
b10000 I
1!
#60000
0!
#65000
b10100 '
b10100 E
b10100 I
1!
#70000
0!
#75000
b11000 '
b11000 E
b11000 I
1!
#80000
0!
#85000
b11100 '
b11100 E
b11100 I
1!
#90000
0!
#95000
b100000 '
b100000 E
b100000 I
1!
#100000
0!
#105000
b100100 '
b100100 E
b100100 I
1!
#110000
0!
#115000
b101000 '
b101000 E
b101000 I
1!
#120000
0!
#125000
b101100 '
b101100 E
b101100 I
1!
#130000
0!
#135000
b110000 '
b110000 E
b110000 I
1!
#140000
0!
#145000
b110100 '
b110100 E
b110100 I
1!
#150000
0!
#155000
b111000 '
b111000 E
b111000 I
1!
#160000
0!
#165000
b111100 '
b111100 E
b111100 I
1!
#170000
0!
#175000
b1000000 '
b1000000 E
b1000000 I
1!
#180000
0!
#185000
b1000100 '
b1000100 E
b1000100 I
1!
#190000
0!
#195000
b1001000 '
b1001000 E
b1001000 I
1!
#200000
0!
#205000
b1001100 '
b1001100 E
b1001100 I
1!
#210000
0!
#215000
b1010000 '
b1010000 E
b1010000 I
1!
